{
  "brandInfo": {
    "id": 725,
    "documentId": "l80fqjoja3vs9rzddkvcihkq",
    "name": "PGO",
    "slug": "pgo",
    "vehicle_type": "moto",
    "isActive": true
  },
  "modelCount": 83,
  "exportDate": "2026-01-07T09:17:53.865Z",
  "models": [
    {
      "id": 29039,
      "documentId": "ror4dyrr7poatvrssrq2a5tn",
      "name": "946",
      "slug": "946",
      "vehicle_type": "moto",
      "isActive": true
    },
    {
      "id": 29812,
      "documentId": "j9odqa3ld164wy2q4ggo0b8j",
      "name": "Bella 125 GT",
      "slug": "bella-125-gt",
      "vehicle_type": "moto",
      "isActive": true
    },
    {
      "id": 29822,
      "documentId": "zi8obp9idikj1s6kenl4kv2i",
      "name": "Beverly 125 (M69)",
      "slug": "beverly-125-m69",
      "vehicle_type": "moto",
      "isActive": true
    },
    {
      "id": 29823,
      "documentId": "upoe3ngqfhzgdyp7vjtyr7v1",
      "name": "Beverly 125 (ZAPM28100)",
      "slug": "beverly-125-zapm28100",
      "vehicle_type": "moto",
      "isActive": true
    },
    {
      "id": 29824,
      "documentId": "am7dk96lakcua5kp0id4jsb9",
      "name": "Beverly 125 GT (ZAPM28100)",
      "slug": "beverly-125-gt-zapm28100",
      "vehicle_type": "moto",
      "isActive": true
    },
    {
      "id": 29825,
      "documentId": "xnewaerlt3ef41ahs6cbja5u",
      "name": "Beverly 125 Tourer (ZAPM28901)",
      "slug": "beverly-125-tourer-zapm28901",
      "vehicle_type": "moto",
      "isActive": true
    },
    {
      "id": 29826,
      "documentId": "v2vvkcmc65qq0t8esk3krqa9",
      "name": "Beverly 200 (ZAPM28200)",
      "slug": "beverly-200-zapm28200",
      "vehicle_type": "moto",
      "isActive": true
    },
    {
      "id": 29827,
      "documentId": "ir2u3iv3icybwx81ovpbrplk",
      "name": "Beverly 200 GT (ZAPM28200)",
      "slug": "beverly-200-gt-zapm28200",
      "vehicle_type": "moto",
      "isActive": true
    },
    {
      "id": 29828,
      "documentId": "mxtoxuy2gtqdlk476vh7ye3w",
      "name": "Beverly 250 Cruiser i.e. (ZAPM28802)",
      "slug": "beverly-250-cruiser-ie-zapm28802",
      "vehicle_type": "moto",
      "isActive": true
    },
    {
      "id": 29829,
      "documentId": "arb4srk4c6gzrhvju7c14bi2",
      "name": "Beverly 250 GT",
      "slug": "beverly-250-gt",
      "vehicle_type": "moto",
      "isActive": true
    },
    {
      "id": 29830,
      "documentId": "dzx75i4id7zspnkmnvhrvtbv",
      "name": "Beverly 250 Tourer (ZAPM28801)",
      "slug": "beverly-250-tourer-zapm28801",
      "vehicle_type": "moto",
      "isActive": true
    },
    {
      "id": 29831,
      "documentId": "blnkqlx4wxlx81titpqs6jv2",
      "name": "Beverly 300 (M69)",
      "slug": "beverly-300-m69",
      "vehicle_type": "moto",
      "isActive": true
    },
    {
      "id": 29832,
      "documentId": "xj8h1bbdfaebl359tgtauth6",
      "name": "Beverly 300 ABS (MA2)",
      "slug": "beverly-300-abs-ma2",
      "vehicle_type": "moto",
      "isActive": true
    },
    {
      "id": 29833,
      "documentId": "lpqylm650sf6r987kpgag1wv",
      "name": "Beverly 300 S Euro 5",
      "slug": "beverly-300-s-euro-5",
      "vehicle_type": "moto",
      "isActive": true
    },
    {
      "id": 29834,
      "documentId": "pczuky4891bol6ha9dkiok38",
      "name": "Beverly 300 Tourer (M28)",
      "slug": "beverly-300-tourer-m28",
      "vehicle_type": "moto",
      "isActive": true
    },
    {
      "id": 29835,
      "documentId": "uztu7myp92r2wqznl56oh9wy",
      "name": "Beverly 350",
      "slug": "beverly-350",
      "vehicle_type": "moto",
      "isActive": true
    },
    {
      "id": 29836,
      "documentId": "dqmwk7um1yz64i28nfwfenlu",
      "name": "Beverly 350 (M69)",
      "slug": "beverly-350-m69",
      "vehicle_type": "moto",
      "isActive": true
    },
    {
      "id": 29837,
      "documentId": "yrala3dx10zgkxd5gs5vqsq1",
      "name": "Beverly 350 ABS (MA2)",
      "slug": "beverly-350-abs-ma2",
      "vehicle_type": "moto",
      "isActive": true
    },
    {
      "id": 29838,
      "documentId": "e3t1vohiub4gf1ifuga8xvlz",
      "name": "Beverly 350 i.e. (MA2)",
      "slug": "beverly-350-ie-ma2",
      "vehicle_type": "moto",
      "isActive": true
    },
    {
      "id": 29839,
      "documentId": "c0pax9j6y5gkkvrexd8imaxe",
      "name": "Beverly 400 (M34)",
      "slug": "beverly-400-m34",
      "vehicle_type": "moto",
      "isActive": true
    },
    {
      "id": 29840,
      "documentId": "e1gfy6tnnrol90a1zczb77a8",
      "name": "Beverly 400 Euro 5",
      "slug": "beverly-400-euro-5",
      "vehicle_type": "moto",
      "isActive": true
    },
    {
      "id": 29841,
      "documentId": "jnw4jpu58lr6j00vcxbxvsps",
      "name": "Beverly 500 (ZAPM34100)",
      "slug": "beverly-500-zapm34100",
      "vehicle_type": "moto",
      "isActive": true
    },
    {
      "id": 29842,
      "documentId": "cb00jwzdwam901zwjslety6o",
      "name": "Beverly 500 Cruiser (ZAPM34500)",
      "slug": "beverly-500-cruiser-zapm34500",
      "vehicle_type": "moto",
      "isActive": true
    },
    {
      "id": 29843,
      "documentId": "zh0tv324uzjaxgdik70mev50",
      "name": "Beverly Tourer 300 (ZAPM28A00)",
      "slug": "beverly-tourer-300-zapm28a00",
      "vehicle_type": "moto",
      "isActive": true
    },
    {
      "id": 29853,
      "documentId": "cn682yb26at566dddtkthgkk",
      "name": "Big Max 50",
      "slug": "big-max-50",
      "vehicle_type": "moto",
      "isActive": true
    },
    {
      "id": 29854,
      "documentId": "phlnv5wmim873y1kahw3xmg4",
      "name": "Big Max 90",
      "slug": "big-max-90",
      "vehicle_type": "moto",
      "isActive": true
    },
    {
      "id": 30809,
      "documentId": "drgeu7ykjo2bjqj2brp898gg",
      "name": "Carnaby 125 (ZAPM60200)",
      "slug": "carnaby-125-zapm60200",
      "vehicle_type": "moto",
      "isActive": true
    },
    {
      "id": 30810,
      "documentId": "vvfq042rv1uulnvils7vfzr4",
      "name": "Carnaby 200 (M60)",
      "slug": "carnaby-200-m60",
      "vehicle_type": "moto",
      "isActive": true
    },
    {
      "id": 30811,
      "documentId": "fkmf42y6bcvkmkhin037xitz",
      "name": "Carnaby 250 (M60)",
      "slug": "carnaby-250-m60",
      "vehicle_type": "moto",
      "isActive": true
    },
    {
      "id": 30812,
      "documentId": "spacqx7aqocn23y2ovgx1qar",
      "name": "Carnaby Cruiser 300 (ZAPM60400)",
      "slug": "carnaby-cruiser-300-zapm60400",
      "vehicle_type": "moto",
      "isActive": true
    },
    {
      "id": 31192,
      "documentId": "nz5kdbeabpiw8tow4429zhxv",
      "name": "Diesis 50 (ZAPC34100)",
      "slug": "diesis-50-zapc34100",
      "vehicle_type": "moto",
      "isActive": true
    },
    {
      "id": 31410,
      "documentId": "xu194uqwdz02iikxrwygdpce",
      "name": "ET2 50 (ZAPC16000)",
      "slug": "et2-50-zapc16000",
      "vehicle_type": "moto",
      "isActive": true
    },
    {
      "id": 31411,
      "documentId": "t36t1xas0kxsu6v1xlosfks4",
      "name": "ET4 125 (ZAPM19000)",
      "slug": "et4-125-zapm19000",
      "vehicle_type": "moto",
      "isActive": true
    },
    {
      "id": 32023,
      "documentId": "fhmktsqnz1tfupu3gztmw7h0",
      "name": "Fly",
      "slug": "fly",
      "vehicle_type": "moto",
      "isActive": true
    },
    {
      "id": 32024,
      "documentId": "umg4hlsfpmo7gxwb6z88an3i",
      "name": "Fly 100 (M53)",
      "slug": "fly-100-m53",
      "vehicle_type": "moto",
      "isActive": true
    },
    {
      "id": 32025,
      "documentId": "syuvwh51y8qkizpsw05kx247",
      "name": "Fly 125",
      "slug": "fly-125",
      "vehicle_type": "moto",
      "isActive": true
    },
    {
      "id": 32026,
      "documentId": "lm702s9k8nnemivpvdqg5xcg",
      "name": "Fly 125 (LBMM57200)",
      "slug": "fly-125-lbmm57200",
      "vehicle_type": "moto",
      "isActive": true
    },
    {
      "id": 32027,
      "documentId": "ad835utskowt3if9io66qj5a",
      "name": "Fly 50",
      "slug": "fly-50",
      "vehicle_type": "moto",
      "isActive": true
    },
    {
      "id": 32028,
      "documentId": "pvcfipw50rtng3jjztjdze3a",
      "name": "Fly 50 4T (LBMC44500)",
      "slug": "fly-50-4t-lbmc44500",
      "vehicle_type": "moto",
      "isActive": true
    },
    {
      "id": 32029,
      "documentId": "hzll953yq38mo3smhvk3u7m8",
      "name": "Fly 50 4T (ZAPC44200)",
      "slug": "fly-50-4t-zapc44200",
      "vehicle_type": "moto",
      "isActive": true
    },
    {
      "id": 32039,
      "documentId": "m0b1di7qatd0xk55y4z9jd7e",
      "name": "Free 1 25 o.Kat (FCS1T)",
      "slug": "free-1-25-okat-fcs1t",
      "vehicle_type": "moto",
      "isActive": true
    },
    {
      "id": 32040,
      "documentId": "lc1zuc6dkpmmso4ow6oz6jll",
      "name": "Free 1 50 m.Kat (FCS1T)",
      "slug": "free-1-50-mkat-fcs1t",
      "vehicle_type": "moto",
      "isActive": true
    },
    {
      "id": 32041,
      "documentId": "fwc8sktbwnifzo9sa05a1s6q",
      "name": "Free FL 25 o.Kat (FCS1T)",
      "slug": "free-fl-25-okat-fcs1t",
      "vehicle_type": "moto",
      "isActive": true
    },
    {
      "id": 32042,
      "documentId": "gt38q87kgq529tbork1229mv",
      "name": "Free FL 50 m.Kat (FCS1T)",
      "slug": "free-fl-50-mkat-fcs1t",
      "vehicle_type": "moto",
      "isActive": true
    },
    {
      "id": 32063,
      "documentId": "r8nsicussk9ri6o8x4081flz",
      "name": "G-Max 125",
      "slug": "g-max-125",
      "vehicle_type": "moto",
      "isActive": true
    },
    {
      "id": 32064,
      "documentId": "k5wi4rzs8u7xdk14fdpire2x",
      "name": "G-Max 25",
      "slug": "g-max-25",
      "vehicle_type": "moto",
      "isActive": true
    },
    {
      "id": 32065,
      "documentId": "hco0udfinxipl0h131ec07jn",
      "name": "G-Max 50",
      "slug": "g-max-50",
      "vehicle_type": "moto",
      "isActive": true
    },
    {
      "id": 32405,
      "documentId": "qy1u9pwpgh7x7ugchevs5mkl",
      "name": "GT 125 L (ZAPM31100)",
      "slug": "gt-125-l-zapm31100",
      "vehicle_type": "moto",
      "isActive": true
    },
    {
      "id": 32406,
      "documentId": "utzd1zuqkk584d1022g4sz07",
      "name": "GT 200 L (ZAPM31200)",
      "slug": "gt-200-l-zapm31200",
      "vehicle_type": "moto",
      "isActive": true
    },
    {
      "id": 32431,
      "documentId": "tmcek3ocktaoikxxc3ckz4ux",
      "name": "GTS",
      "slug": "gts",
      "vehicle_type": "moto",
      "isActive": true
    },
    {
      "id": 32433,
      "documentId": "ttn9k2ja3m09n8vtqqh46xt7",
      "name": "GTS 125 Super i.e. (ZAPM45300)",
      "slug": "gts-125-super-ie-zapm45300",
      "vehicle_type": "moto",
      "isActive": true
    },
    {
      "id": 32434,
      "documentId": "cc8doj2auqpii89i3h3n728f",
      "name": "GTS 125 i.e. (ZAPM31300)",
      "slug": "gts-125-ie-zapm31300",
      "vehicle_type": "moto",
      "isActive": true
    },
    {
      "id": 32435,
      "documentId": "wxq81n66kno2bgqe0wemsfmr",
      "name": "GTS 250",
      "slug": "gts-250",
      "vehicle_type": "moto",
      "isActive": true
    },
    {
      "id": 32436,
      "documentId": "awuex7wwk0zcb3cnrgz8kq1a",
      "name": "GTS 250 i.e.",
      "slug": "gts-250-ie",
      "vehicle_type": "moto",
      "isActive": true
    },
    {
      "id": 32437,
      "documentId": "rbcl8wb4yacej8zefhsmkydi",
      "name": "GTS 300 (ZAPM45200)",
      "slug": "gts-300-zapm45200",
      "vehicle_type": "moto",
      "isActive": true
    },
    {
      "id": 32438,
      "documentId": "v65f3hehs9xgconjre5buqui",
      "name": "GTS 300 ABS",
      "slug": "gts-300-abs",
      "vehicle_type": "moto",
      "isActive": true
    },
    {
      "id": 32439,
      "documentId": "tgr8dykxwx0r8zpspc8pye0r",
      "name": "GTS 300 ABS (MA3C)",
      "slug": "gts-300-abs-ma3c",
      "vehicle_type": "moto",
      "isActive": true
    },
    {
      "id": 32440,
      "documentId": "sflprehx4gg82rt8jnywkqqb",
      "name": "GTS 300 Super (M45)",
      "slug": "gts-300-super-m45",
      "vehicle_type": "moto",
      "isActive": true
    },
    {
      "id": 32445,
      "documentId": "z5ewe3bu86c6elcboa2j1oxm",
      "name": "GTV 125 (ZAPM31301)",
      "slug": "gtv-125-zapm31301",
      "vehicle_type": "moto",
      "isActive": true
    },
    {
      "id": 32446,
      "documentId": "ofh0y7odjqrlsd9g2y7r14cp",
      "name": "GTV 250 i.e. (ZAPM45102)",
      "slug": "gtv-250-ie-zapm45102",
      "vehicle_type": "moto",
      "isActive": true
    },
    {
      "id": 32447,
      "documentId": "gaxpmovps1qpicgk3y1yveen",
      "name": "GTV 300 Super (M45)",
      "slug": "gtv-300-super-m45",
      "vehicle_type": "moto",
      "isActive": true
    },
    {
      "id": 32450,
      "documentId": "ywv1u4z1lqgm3dgdmbp5syo2",
      "name": "GTX 125 (ZAPM20000)",
      "slug": "gtx-125-zapm20000",
      "vehicle_type": "moto",
      "isActive": true
    },
    {
      "id": 32451,
      "documentId": "lvwvvpv8dvar6as7ru6v1q0c",
      "name": "GTX 180 (ZAPM20000)",
      "slug": "gtx-180-zapm20000",
      "vehicle_type": "moto",
      "isActive": true
    },
    {
      "id": 32486,
      "documentId": "z4x8gqs38rnbk8bhrgzmrall",
      "name": "Grillo 25 (CXM1T)",
      "slug": "grillo-25-cxm1t",
      "vehicle_type": "moto",
      "isActive": true
    },
    {
      "id": 32588,
      "documentId": "zpfcdof0vt60ronw5fozrj1p",
      "name": "Hexagon 125 2T (EXS1T)",
      "slug": "hexagon-125-2t-exs1t",
      "vehicle_type": "moto",
      "isActive": true
    },
    {
      "id": 32589,
      "documentId": "hjh0pyubpp48015ukncwi0vr",
      "name": "Hexagon 125 4T (ZAPM20000)",
      "slug": "hexagon-125-4t-zapm20000",
      "vehicle_type": "moto",
      "isActive": true
    },
    {
      "id": 32590,
      "documentId": "uz00w7gb7vjhnsxd77zrb0z9",
      "name": "Hexagon 125 LX (ZAPM05000)",
      "slug": "hexagon-125-lx-zapm05000",
      "vehicle_type": "moto",
      "isActive": true
    },
    {
      "id": 33258,
      "documentId": "y0gfmo0oqdu0risv5sq56lym",
      "name": "Ligero 100",
      "slug": "ligero-100",
      "vehicle_type": "moto",
      "isActive": true
    },
    {
      "id": 33259,
      "documentId": "agpvnwadauhg4gvl6ybbdxib",
      "name": "Ligero 125",
      "slug": "ligero-125",
      "vehicle_type": "moto",
      "isActive": true
    },
    {
      "id": 33260,
      "documentId": "fy7nvmmv6k8iekrfkb4ifbo8",
      "name": "Ligero 50",
      "slug": "ligero-50",
      "vehicle_type": "moto",
      "isActive": true
    },
    {
      "id": 34307,
      "documentId": "av0bb3jkbyi5seb4uach26wm",
      "name": "PM-S 50",
      "slug": "pm-s-50",
      "vehicle_type": "moto",
      "isActive": true
    },
    {
      "id": 34308,
      "documentId": "ocbqug9608tn2ix96igz0qbx",
      "name": "PM-X 50",
      "slug": "pm-x-50",
      "vehicle_type": "moto",
      "isActive": true
    },
    {
      "id": 34912,
      "documentId": "wk3gtscgk78bs7r17im5fmuo",
      "name": "RodoShow 25",
      "slug": "rodoshow-25",
      "vehicle_type": "moto",
      "isActive": true
    },
    {
      "id": 34913,
      "documentId": "ypy9yenc7q66ex7002vpxq14",
      "name": "RodoShow 50",
      "slug": "rodoshow-50",
      "vehicle_type": "moto",
      "isActive": true
    },
    {
      "id": 35736,
      "documentId": "p5b8e9nwz60bz0rk079pgfcq",
      "name": "Star 50",
      "slug": "star-50",
      "vehicle_type": "moto",
      "isActive": true
    },
    {
      "id": 35737,
      "documentId": "x9fotsxd67k8rdz1bogztlo7",
      "name": "Star 80",
      "slug": "star-80",
      "vehicle_type": "moto",
      "isActive": true
    },
    {
      "id": 35788,
      "documentId": "tyaawabfyu4croihvqkrrv5m",
      "name": "T-Rex 25",
      "slug": "t-rex-25",
      "vehicle_type": "moto",
      "isActive": true
    },
    {
      "id": 35789,
      "documentId": "j6umc02shgxu96034pa5m61p",
      "name": "T.Rex 4T 150",
      "slug": "trex-4t-150",
      "vehicle_type": "moto",
      "isActive": true
    },
    {
      "id": 35790,
      "documentId": "h6hlhk441b1ie128j8xbugg2",
      "name": "T.Rex 50",
      "slug": "trex-50",
      "vehicle_type": "moto",
      "isActive": true
    },
    {
      "id": 36051,
      "documentId": "nb498lj6sssh8s5k2xi47ioc",
      "name": "TR3 25",
      "slug": "tr3-25",
      "vehicle_type": "moto",
      "isActive": true
    },
    {
      "id": 36052,
      "documentId": "xohh7e3aihwur2pfam29k42v",
      "name": "TR3 50",
      "slug": "tr3-50",
      "vehicle_type": "moto",
      "isActive": true
    },
    {
      "id": 36256,
      "documentId": "v65kfmqnxubr3bvx7uhqbpft",
      "name": "Tornado 50",
      "slug": "tornado-50",
      "vehicle_type": "moto",
      "isActive": true
    },
    {
      "id": 36257,
      "documentId": "o5qt1fx1606o1n1via8m75jo",
      "name": "Tornado 90 1.25",
      "slug": "tornado-90-125",
      "vehicle_type": "moto",
      "isActive": true
    }
  ]
}